{
  "en": {
    "logincard_welcome text-1": "Welcome to",
    "logincard_welcome text-2": ". Please login with your campus mail address.",
    "logincard_login button": "Login",
    "logincard_password placeholder": "Password",
    "logincard_register text": "New here?",
    "logincard_register button": "Register",

    "groupdetail_create group": "Create new group",
    "groupdetail_group comment": "You have to be 4 people to create a new group.",
    "groupdetail_write mail": "Send an e-mail",

    "groupcard_tritt bei": "Join a group now!",

    "notifications-card none": "No notifications.",

    "mainview_praktikum typ": "Photo ",

    "c_medientechnik": "Media Technology"
  },

  "de": {
    "logincard_welcome text-1": "Willkommen bei ",
    "logincard_welcome text-2": ". Bitte logge dich mit deiner Campus Mail-Adresse ein.",
    "logincard_login button": "Einloggen",
    "logincard_password placeholder": "Passwort",
    "logincard_register text": "Neu hier?",
    "logincard_register button": "Registrieren",

    "groupdetail_create group": "Neue Gruppe Erstellen",
    "groupdetail_group comment": "Ihr müsst zu viert sein, um eine neue Gruppe zu erstellen.",
    "groupdetail_write mail": "E-Mail senden",

    "groupcard_tritt bei": "Tritt jetzt einer Gruppe bei!",

    "notifications-card none": "Keine Benachrichtigungen.",

    "mainview_praktikum typ": "Photo ",

    "c_medientechnik": "Medientechnik"
    }
}